nlshell/__init__.py
nlshell/main.py
nlshell/settings.py
nlshell-0.1.1.dist-info/LICENSE
nlshell-0.1.1.dist-info/METADATA
nlshell-0.1.1.dist-info/WHEEL
nlshell-0.1.1.dist-info/entry_points.txt
nlshell-0.1.1.dist-info/RECORD
