Metadata-Version: 2.1
Name: nlshell
Version: 0.1.1
Summary: Creates shell command from a description using an LLM
License: MIT
Author: Mattias Brycke
Author-email: mattias.brycke@gmail.com
Requires-Python: >=3.10,<4.0
Classifier: License :: OSI Approved :: MIT License
Classifier: Programming Language :: Python :: 3
Classifier: Programming Language :: Python :: 3.10
Classifier: Programming Language :: Python :: 3.11
Classifier: Programming Language :: Python :: 3.12
Classifier: Programming Language :: Python :: 3.13
Requires-Dist: openai (>=1.52.2,<2.0.0)
